proclaunch/__init__.py
proclaunch/nt.py
proclaunch/posix.py
proclaunch-0.1.0.dist-info/licenses/LICENSE
proclaunch-0.1.0.dist-info/METADATA
proclaunch-0.1.0.dist-info/WHEEL
proclaunch-0.1.0.dist-info/top_level.txt
proclaunch-0.1.0.dist-info/RECORD
