Metadata-Version: 2.4
Name: proclaunch
Version: 0.1.0
Summary: A minimal interface over C for launching OS processes in Python 2 and 3 and across Windows and Unix, without invoking a shell or relying on Python's overly abstract `subprocess` module.
Author-email: Jifeng Wu <jifengwu2k@gmail.com>
License-Expression: MIT
Project-URL: Homepage, https://github.com/jifengwu2k/proclaunch
Project-URL: Bug Tracker, https://github.com/jifengwu2k/proclaunch/issues
Classifier: Programming Language :: Python :: 2
Classifier: Programming Language :: Python :: 3
Classifier: Operating System :: OS Independent
Requires-Python: >=2
License-File: LICENSE
Dynamic: license-file
